FPGA/ADC_ip.v
// Code your design here
`timescale 1ns / 1ps

module ADC(
  
	input clk, rst, we,
  	input [13:0] bn,
  	output reg adc_clk,
	output reg trigger
  
);

	reg [10:0] internal_count = 0;
 
 
  	reg [13:0] s1_1, s1_2, s1_3, s1_4;
  	reg [13:0] s2_1, s2_2, s2_3, s2_4;
  	reg [13:0] s3_1, s3_2, s3_3, s3_4;
  	reg [13:0] s4_1, s4_2, s4_3, s4_4;
  	reg [13:0] s5_1, s5_2, s5_3, s5_4;

  	localparam adc_setting_cycles = 100; // clk = 200 MHz

	//clk_div
	localparam clk_div = 20; //20+, 20-

  	//post setting time (sub sampling intervals)
  	localparam cycles_for_s1 = 20; //s1
  	localparam cycles_for_s2 = 19; //s2
  	localparam cycles_for_s3 = 18; //s3
  	localparam cycles_for_s4 = 17; //s4
  	localparam cycles_for_s5 = 16; //s5

	// ----- clk div logic begin (10MHz) ----- //

always @(posedge clk) begin
	if (rst) begin
		adc_clk <= 0;
	end

	else begin
	 	if(we) begin
			internal_count = internal_count + 1; //up counter

			if (internal_count < ((clk_div >> 1))) begin
				adc_clk <= 0;
			end

			if (internal_count > (clk_div >> 1)) begin
				adc_clk <= 1;

				if (internal_count == clk_div )
					internal_count <= 0; //reset
			end

	 	end
	end
end

// ----- clk div logic end ----- //


		// s1_1 <= 0;
		// s1_2 <= 0;
		// s1_3 <= 0;
		// s1_4 <= 0;

		// s2_1 <= 0;
		// s2_2 <= 0;
		// s2_3 <= 0;
		// s2_4 <= 0;

		// s3_1 <= 0;
		// s3_2 <= 0;
		// s3_3 <= 0;
		// s3_4 <= 0;

		// s4_1 <= 0;
		// s4_2 <= 0;
		// s4_3 <= 0;
		// s4_4 <= 0;

		// s5_1 <= 0;
		// s5_2 <= 0;
		// s5_3 <= 0;
		// s5_4 <= 0;

// ----- trigger logic begin ----- //


// ----- trigger logic end ----- //

endmodule

FPGA/tb_ADC_ip.v

`timescale 1ns / 1ps
module ADC_test ();

	reg clk, rst, we;
  	reg [13:0] bn;
  	wire adc_clk;
	wire trigger;


    // instatiation of dut

    ADC dut(clk, rst, we, bn, adc_clk, trigger);


    //initial values
    initial begin
        clk = 0;
        rst = 0;
        we = 1;
        bn = 0;
    end

    // clk gen
    always #2.5 clk = ~clk;

    // ----- stimulus start ---- //

    initial begin
    //put rst
    rst = 1;			//set rst
    @(negedge clk);	//wait for negedge clk
    
        rst = 0;			//set rst = 0
        we = 1;			//set we
    
    //$monitor("counter value: %d",data_out);
    
    #630 $finish;
    
    end
    // ----- stimulus start ---- //

    //dump to file
    initial begin
        $dumpfile ("ADC.vcd");
    $dumpvars;
    end

endmodule

FPGA/ADC.vcd
$date
	Wed Nov 10 20:40:58 2021
$end
$version
	Icarus Verilog
$end
$timescale
	1ps
$end
$scope module ADC_test $end
$var wire 1 ! trigger $end
$var wire 1 " adc_clk $end
$var reg 14 # bn [13:0] $end
$var reg 1 $ clk $end
$var reg 1 % rst $end
$var reg 1 & we $end
$scope module dut $end
$var wire 14 ' bn [13:0] $end
$var wire 1 $ clk $end
$var wire 1 % rst $end
$var wire 1 & we $end
$var reg 1 " adc_clk $end
$var reg 11 ( internal_count [10:0] $end
$var reg 14 ) s1_1 [13:0] $end
$var reg 14 * s1_2 [13:0] $end
$var reg 14 + s1_3 [13:0] $end
$var reg 14 , s1_4 [13:0] $end
$var reg 14 - s2_1 [13:0] $end
$var reg 14 . s2_2 [13:0] $end
$var reg 14 / s2_3 [13:0] $end
$var reg 14 0 s2_4 [13:0] $end
$var reg 14 1 s3_1 [13:0] $end
$var reg 14 2 s3_2 [13:0] $end
$var reg 14 3 s3_3 [13:0] $end
$var reg 14 4 s3_4 [13:0] $end
$var reg 14 5 s4_1 [13:0] $end
$var reg 14 6 s4_2 [13:0] $end
$var reg 14 7 s4_3 [13:0] $end
$var reg 14 8 s4_4 [13:0] $end
$var reg 14 9 s5_1 [13:0] $end
$var reg 14 : s5_2 [13:0] $end
$var reg 14 ; s5_3 [13:0] $end
$var reg 14 < s5_4 [13:0] $end
$var reg 1 ! trigger $end
$upscope $end
$upscope $end
$enddefinitions $end
#0
$dumpvars
bx <
bx ;
bx :
bx 9
bx 8
bx 7
bx 6
bx 5
bx 4
bx 3
bx 2
bx 1
bx 0
bx /
bx .
bx -
bx ,
bx +
bx *
bx )
b0 (
b0 '
1&
1%
0$
b0 #
x"
x!
$end
#2500
b0 <
b0 ;
b0 :
b0 9
b0 8
b0 7
b0 6
b0 5
b0 4
b0 3
b0 2
b0 1
b0 0
b0 /
b0 .
b0 -
b0 ,
b0 +
b0 *
b0 )
0!
0"
1$
#5000
0%
0$
#7500
b1 (
1$
#10000
0$
#12500
b10 (
1$
#15000
0$
#17500
b11 (
1$
#20000
0$
#22500
b100 (
1$
#25000
0$
#27500
b101 (
1$
#30000
0$
#32500
b110 (
1$
#35000
0$
#37500
b111 (
1$
#40000
0$
#42500
b1000 (
1$
#45000
0$
#47500
b1001 (
1$
#50000
0$
#52500
b1010 (
1$
#55000
0$
#57500
1"
b1011 (
1$
#60000
0$
#62500
b1100 (
1$
#65000
0$
#67500
b1101 (
1$
#70000
0$
#72500
b1110 (
1$
#75000
0$
#77500
b1111 (
1$
#80000
0$
#82500
b10000 (
1$
#85000
0$
#87500
b10001 (
1$
#90000
0$
#92500
b10010 (
1$
#95000
0$
#97500
b10011 (
1$
#100000
0$
#102500
b0 (
1$
#105000
0$
#107500
0"
b1 (
1$
#110000
0$
#112500
b10 (
1$
#115000
0$
#117500
b11 (
1$
#120000
0$
#122500
b100 (
1$
#125000
0$
#127500
b101 (
1$
#130000
0$
#132500
b110 (
1$
#135000
0$
#137500
b111 (
1$
#140000
0$
#142500
b1000 (
1$
#145000
0$
#147500
b1001 (
1$
#150000
0$
#152500
b1010 (
1$
#155000
0$
#157500
1"
b1011 (
1$
#160000
0$
#162500
b1100 (
1$
#165000
0$
#167500
b1101 (
1$
#170000
0$
#172500
b1110 (
1$
#175000
0$
#177500
b1111 (
1$
#180000
0$
#182500
b10000 (
1$
#185000
0$
#187500
b10001 (
1$
#190000
0$
#192500
b10010 (
1$
#195000
0$
#197500
b10011 (
1$
#200000
0$
#202500
b0 (
1$
#205000
0$
#207500
0"
b1 (
1$
#210000
0$
#212500
b10 (
1$
#215000
0$
#217500
b11 (
1$
#220000
0$
#222500
b100 (
1$
#225000
0$
#227500
b101 (
1$
#230000
0$
#232500
b110 (
1$
#235000
0$
#237500
b111 (
1$
#240000
0$
#242500
b1000 (
1$
#245000
0$
#247500
b1001 (
1$
#250000
0$
#252500
b1010 (
1$
#255000
0$
#257500
1"
b1011 (
1$
#260000
0$
#262500
b1100 (
1$
#265000
0$
#267500
b1101 (
1$
#270000
0$
#272500
b1110 (
1$
#275000
0$
#277500
b1111 (
1$
#280000
0$
#282500
b10000 (
1$
#285000
0$
#287500
b10001 (
1$
#290000
0$
#292500
b10010 (
1$
#295000
0$
#297500
b10011 (
1$
#300000
0$
#302500
b0 (
1$
#305000
0$
#307500
0"
b1 (
1$
#310000
0$
#312500
b10 (
1$
#315000
0$
#317500
b11 (
1$
#320000
0$
#322500
b100 (
1$
#325000
0$
#327500
b101 (
1$
#330000
0$
#332500
b110 (
1$
#335000
0$
#337500
b111 (
1$
#340000
0$
#342500
b1000 (
1$
#345000
0$
#347500
b1001 (
1$
#350000
0$
#352500
b1010 (
1$
#355000
0$
#357500
1"
b1011 (
1$
#360000
0$
#362500
b1100 (
1$
#365000
0$
#367500
b1101 (
1$
#370000
0$
#372500
b1110 (
1$
#375000
0$
#377500
b1111 (
1$
#380000
0$
#382500
b10000 (
1$
#385000
0$
#387500
b10001 (
1$
#390000
0$
#392500
b10010 (
1$
#395000
0$
#397500
b10011 (
1$
#400000
0$
#402500
b0 (
1$
#405000
0$
#407500
0"
b1 (
1$
#410000
0$
#412500
b10 (
1$
#415000
0$
#417500
b11 (
1$
#420000
0$
#422500
b100 (
1$
#425000
0$
#427500
b101 (
1$
#430000
0$
#432500
b110 (
1$
#435000
0$
#437500
b111 (
1$
#440000
0$
#442500
b1000 (
1$
#445000
0$
#447500
b1001 (
1$
#450000
0$
#452500
b1010 (
1$
#455000
0$
#457500
1"
b1011 (
1$
#460000
0$
#462500
b1100 (
1$
#465000
0$
#467500
b1101 (
1$
#470000
0$
#472500
b1110 (
1$
#475000
0$
#477500
b1111 (
1$
#480000
0$
#482500
b10000 (
1$
#485000
0$
#487500
b10001 (
1$
#490000
0$
#492500
b10010 (
1$
#495000
0$
#497500
b10011 (
1$
#500000
0$
#502500
b0 (
1$
#505000
0$
#507500
0"
b1 (
1$
#510000
0$
#512500
b10 (
1$
#515000
0$
#517500
b11 (
1$
#520000
0$
#522500
b100 (
1$
#525000
0$
#527500
b101 (
1$
#530000
0$
#532500
b110 (
1$
#535000
0$
#537500
b111 (
1$
#540000
0$
#542500
b1000 (
1$
#545000
0$
#547500
b1001 (
1$
#550000
0$
#552500
b1010 (
1$
#555000
0$
#557500
1"
b1011 (
1$
#560000
0$
#562500
b1100 (
1$
#565000
0$
#567500
b1101 (
1$
#570000
0$
#572500
b1110 (
1$
#575000
0$
#577500
b1111 (
1$
#580000
0$
#582500
b10000 (
1$
#585000
0$
#587500
b10001 (
1$
#590000
0$
#592500
b10010 (
1$
#595000
0$
#597500
b10011 (
1$
#600000
0$
#602500
b0 (
1$
#605000
0$
#607500
0"
b1 (
1$
#610000
0$
#612500
b10 (
1$
#615000
0$
#617500
b11 (
1$
#620000
0$
#622500
b100 (
1$
#625000
0$
#627500
b101 (
1$
#630000
0$
#632500
b110 (
1$
